Metadata-Version: 1.0
Name: dada-text
Version: 0.0.9
Summary: re-usable text processing utilities for dada-lake
Home-page: http://globally.ltd
Author: gltd
Author-email: hey@gltd.email
License: UNKNOWN
Platform: UNKNOWN
